CHANGES.txt
MANIFEST.in
README.rst
setup.py
PyVEP.egg-info/PKG-INFO
PyVEP.egg-info/SOURCES.txt
PyVEP.egg-info/dependency_links.txt
PyVEP.egg-info/not-zip-safe
PyVEP.egg-info/requires.txt
PyVEP.egg-info/top_level.txt
vep/__init__.py
vep/_m2_monkeypatch.py
vep/errors.py
vep/jwt.py
vep/utils.py
vep/tests/__init__.py
vep/tests/test_jwt.py
vep/tests/test_m2_monkeypatch.py
vep/tests/test_utils.py
vep/tests/test_verifiers.py
vep/tests/certs/localhost.crt
vep/tests/certs/localhost.key
vep/tests/certs/selfsigned.crt
vep/tests/certs/selfsigned.key
vep/verifiers/__init__.py
vep/verifiers/dummy.py
vep/verifiers/local.py
vep/verifiers/remote.py
vep/verifiers/workerpool.py