Metadata-Version: 1.0
Name: PyVEP
Version: 0.3.2
Summary: Python library for the Verified Email Protocol
Home-page: https://github.com/mozilla/PyVEP
Author: Mozilla Identity Team
Author-email: dev-identity@lists.mozilla.org
License: MPLv2.0
Keywords: authentication vep browserid login email
Platform: UNKNOWN
Classifier: Programming Language :: Python
Classifier: License :: OSI Approved :: Mozilla Public License 2.0 (MPL 2.0)
